mensajes/__init__.py
mensajes/adios/__init__.py
mensajes/adios/despedidas.py
mensajes/hola/__init__.py
mensajes/hola/saludos.py
Mensajes_Axl_Bravo.365-6.0.dist-info/METADATA
Mensajes_Axl_Bravo.365-6.0.dist-info/WHEEL
Mensajes_Axl_Bravo.365-6.0.dist-info/top_level.txt
Mensajes_Axl_Bravo.365-6.0.dist-info/RECORD
