Metadata-Version: 2.1
Name: Mensajes-Axl-Bravo.365
Version: 6.0
Summary: Un paquete para saludar y despedir
Home-page: 
Author: Axl Bravo
Author-email: axl@hmail.com
Classifier: Environment :: Console
Classifier: Programming Language :: Python :: 3.9
Classifier: Programming Language :: Python :: Implementation :: PyPy
Requires-Dist: numpy (>=1.23.3)
